pelican_dashify/__init__.py
pelican_dashify/dashify.py
pelican_dashify/exceptions.py
pelican_dashify/filters.py
pelican_dashify/settings.py
pelican_dashify-0.1.2.dist-info/LICENSE
pelican_dashify-0.1.2.dist-info/METADATA
pelican_dashify-0.1.2.dist-info/WHEEL
pelican_dashify-0.1.2.dist-info/top_level.txt
pelican_dashify-0.1.2.dist-info/RECORD
